{"type":"FeatureCollection","features":[{"type":"Feature","id":15592,"geometry":{"type":"Point","coordinates":[-73.1621217209999,-37.0855196809999]},"properties":{"OBJECTID":15592,"nombre_pe":null,"cine_prov":"081","cine_com":"08106","nom_com":"Lota","nom_prov":"Concepción","nom_reg":"Biobío","cine_reg":"08","tipo":"PE","name":"08106PE008","sector":"Lota"}},{"type":"Feature","id":15572,"geometry":{"type":"Point","coordinates":[-73.137582365,-37.06047203]},"properties":{"OBJECTID":15572,"nombre_pe":null,"cine_prov":"081","cine_com":"08102","nom_com":"Coronel","nom_prov":"Concepción","nom_reg":"Biobío","cine_reg":"08","tipo":"PE","name":"08102PE023","sector":"Playa Blanca"}},{"type":"Feature","id":15589,"geometry":{"type":"Point","coordinates":[-73.1556271749999,-37.075449529]},"properties":{"OBJECTID":15589,"nombre_pe":null,"cine_prov":"081","cine_com":"08106","nom_com":"Lota","nom_prov":"Concepción","nom_reg":"Biobío","cine_reg":"08","tipo":"PE","name":"08106PE001","sector":"Lota"}},{"type":"Feature","id":15573,"geometry":{"type":"Point","coordinates":[-73.138834436,-37.0637870699999]},"properties":{"OBJECTID":15573,"nombre_pe":null,"cine_prov":"081","cine_com":"08102","nom_com":"Coronel","nom_prov":"Concepción","nom_reg":"Biobío","cine_reg":"08","tipo":"PE","name":"08102PE024","sector":"Playa Blanca"}},{"type":"Feature","id":15570,"geometry":{"type":"Point","coordinates":[-73.1422206839999,-37.049095665]},"properties":{"OBJECTID":15570,"nombre_pe":null,"cine_prov":"081","cine_com":"08102","nom_com":"Coronel","nom_prov":"Concepción","nom_reg":"Biobío","cine_reg":"08","tipo":"PE","name":"08102PE021","sector":"Coronel"}},{"type":"Feature","id":15590,"geometry":{"type":"Point","coordinates":[-73.156260456,-37.076614454]},"properties":{"OBJECTID":15590,"nombre_pe":null,"cine_prov":"081","cine_com":"08106","nom_com":"Lota","nom_prov":"Concepción","nom_reg":"Biobío","cine_reg":"08","tipo":"PE","name":"08106PE002","sector":"Lota"}},{"type":"Feature","id":15593,"geometry":{"type":"Point","coordinates":[-73.1660270419999,-37.082465531]},"properties":{"OBJECTID":15593,"nombre_pe":null,"cine_prov":"081","cine_com":"08106","nom_com":"Lota","nom_prov":"Concepción","nom_reg":"Biobío","cine_reg":"08","tipo":"PE","name":"08106PE003","sector":"Lota"}},{"type":"Feature","id":15587,"geometry":{"type":"Point","coordinates":[-73.152004677,-37.092152126]},"properties":{"OBJECTID":15587,"nombre_pe":null,"cine_prov":"081","cine_com":"08106","nom_com":"Lota","nom_prov":"Concepción","nom_reg":"Biobío","cine_reg":"08","tipo":"PE","name":"08106PE007","sector":"Lota"}},{"type":"Feature","id":15588,"geometry":{"type":"Point","coordinates":[-73.168171733,-37.082213915]},"properties":{"OBJECTID":15588,"nombre_pe":null,"cine_prov":"081","cine_com":"08106","nom_com":"Lota","nom_prov":"Concepción","nom_reg":"Biobío","cine_reg":"08","tipo":"PE","name":"08106PE005","sector":"Lota"}},{"type":"Feature","id":15571,"geometry":{"type":"Point","coordinates":[-73.1386757029999,-37.05504991]},"properties":{"OBJECTID":15571,"nombre_pe":null,"cine_prov":"081","cine_com":"08102","nom_com":"Coronel","nom_prov":"Concepción","nom_reg":"Biobío","cine_reg":"08","tipo":"PE","name":"08102PE022","sector":"Coronel"}},{"type":"Feature","id":15591,"geometry":{"type":"Point","coordinates":[-73.1654326569999,-37.082569518]},"properties":{"OBJECTID":15591,"nombre_pe":null,"cine_prov":"081","cine_com":"08106","nom_com":"Lota","nom_prov":"Concepción","nom_reg":"Biobío","cine_reg":"08","tipo":"PE","name":"08106PE004","sector":"Lota"}},{"type":"Feature","id":15586,"geometry":{"type":"Point","coordinates":[-73.1607093809999,-37.088659228]},"properties":{"OBJECTID":15586,"nombre_pe":null,"cine_prov":"081","cine_com":"08106","nom_com":"Lota","nom_prov":"Concepción","nom_reg":"Biobío","cine_reg":"08","tipo":"PE","name":"08106PE006","sector":"Lota"}},{"type":"Feature","id":15574,"geometry":{"type":"Point","coordinates":[-73.1416008419999,-37.0675554819999]},"properties":{"OBJECTID":15574,"nombre_pe":null,"cine_prov":"081","cine_com":"08102","nom_com":"Coronel","nom_prov":"Concepción","nom_reg":"Biobío","cine_reg":"08","tipo":"PE","name":"08102PE025","sector":"Playa Blanca"}}]}